simple_math/__init__.py
simple_math/math.py
d_simple_math-0.1.1.dist-info/METADATA
d_simple_math-0.1.1.dist-info/WHEEL
d_simple_math-0.1.1.dist-info/top_level.txt
d_simple_math-0.1.1.dist-info/RECORD
