Metadata-Version: 2.1
Name: d-simple-math
Version: 0.1.1
Summary: A very simple math library
Home-page: UNKNOWN
Author: deepa_r
Author-email: deepa@palmtreeinfotech.com
License: UNKNOWN
Platform: UNKNOWN
